thunno2/__init__.py
thunno2/autoexplanation.py
thunno2/canvas.py
thunno2/codepage.py
thunno2/commands.py
thunno2/constants.py
thunno2/dictionary.py
thunno2/flags.py
thunno2/helpers.py
thunno2/interpreter.py
thunno2/lexer.py
thunno2/run.py
thunno2/tests.py
thunno2/tokens.py
thunno2/version.py
thunno2-2.2.33.dist-info/METADATA
thunno2-2.2.33.dist-info/WHEEL
thunno2-2.2.33.dist-info/entry_points.txt
thunno2-2.2.33.dist-info/top_level.txt
thunno2-2.2.33.dist-info/RECORD
