Metadata-Version: 2.1
Name: thunno2
Version: 2.2.33
Summary: A golfing language
Home-page: https://github.com/Thunno/Thunno2
Download-URL: https://github.com/Thunno/Thunno2/archive/refs/tags/v2.2.33.tar.gz
Author: Rujul Nayak
Author-email: rujulnayak@outlook.com
License: MIT
Keywords: golfing,code-golf,language
Classifier: Development Status :: 3 - Alpha
Classifier: Intended Audience :: Developers
Classifier: Topic :: Software Development :: Build Tools
Classifier: License :: OSI Approved :: MIT License
Classifier: Programming Language :: Python :: 3
Classifier: Programming Language :: Python :: 3.6
Classifier: Programming Language :: Python :: 3.7
Classifier: Programming Language :: Python :: 3.8
Classifier: Programming Language :: Python :: 3.9
Classifier: Programming Language :: Python :: 3.10
